newstudiolowbadgetlibrary/__init__.py
newstudiolowbadgetlibrary/main.py
newstudiolowbadgetlibrary-0.2.0.dist-info/METADATA
newstudiolowbadgetlibrary-0.2.0.dist-info/WHEEL
newstudiolowbadgetlibrary-0.2.0.dist-info/RECORD
