Metadata-Version: 2.3
Name: newstudiolowbadgetlibrary
Version: 0.2.0
Summary: 
Author: LowBadget-Studio-LLC
Author-email: LowBadget-Studio-LLC@outlook.com
Requires-Python: >=3.12
Classifier: Programming Language :: Python :: 3
Classifier: Programming Language :: Python :: 3.12
Classifier: Programming Language :: Python :: 3.13
Requires-Dist: pygame (>=2.6.1,<3.0.0)
